{
  "Collisions and Momentum": {
    "1": "conservation of momentum",
    "2": "elastic collisions and kinetic energy conservation",
    "3": "energy dissipation (heat & deformation)",
    "4": "effects of mass ratio in collisions",
    "5": "coefficient of restitution and velocity ratios"
  },
  "Pendulum Basics": {
    "1": "definition of a simple pendulum and its assumptions",
    "2": "dependence of period on length (small-angle approximation)",
    "3": "time period formula: T = 2π√(L/g)",
    "4": "scaling of period with length (square-root dependence)",
    "5": "energy interchange between kinetic and potential energy"
  }
}
